<?xml version="1.0" encoding="UTF-8"?>
<ticket>
  <assigned-user-id type="integer" nil="true"></assigned-user-id>
  <attachments-count type="integer">0</attachments-count>
  <closed type="boolean">false</closed>
  <created-at type="datetime">2011-05-13T07:35:24+09:00</created-at>
  <creator-id type="integer">2503</creator-id>
  <milestone-due-on type="datetime" nil="true"></milestone-due-on>
  <milestone-id type="integer">90248</milestone-id>
  <number type="integer">252</number>
  <permalink>notations-add-ability-to-use-wysiwyg-in-help</permalink>
  <priority type="integer">1</priority>
  <project-id type="integer">30780</project-id>
  <raw-data type="binary" nil="true" encoding="base64"></raw-data>
  <state>new</state>
  <tag nil="true"></tag>
  <title>Notations &gt; Add ability to use wysiwyg in Help</title>
  <updated-at type="datetime">2011-05-13T07:36:03+09:00</updated-at>
  <user-id type="integer">2503</user-id>
  <version type="integer">1</version>
  <user-name>Anatole</user-name>
  <creator-name>Anatole</creator-name>
  <url>http://theplant.lighthouseapp.com/projects/30780/tickets/252</url>
  <milestone-title>Next Milestone?</milestone-title>
  <priority-name>High</priority-name>
  <original-body>If we could add pictures and such in the Help secion it would make it so that we would radically improve the Help feature.</original-body>
  <latest-body>If we could add pictures and such in the Help secion it would make it so that we would radically improve the Help feature.</latest-body>
  <original-body-html>&lt;div&gt;&lt;p&gt;If we could add pictures and such in the Help secion it would
make it so that we would radically improve the Help feature.&lt;/p&gt;&lt;/div&gt;</original-body-html>
  <versions type="array">
    <version type="Ticket::Version">
      <assigned-user-id type="integer" nil="true"></assigned-user-id>
      <attachments-count type="integer">0</attachments-count>
      <body>If we could add pictures and such in the Help secion it would make it so that we would radically improve the Help feature.</body>
      <body-html>&lt;div&gt;&lt;p&gt;If we could add pictures and such in the Help secion it would
make it so that we would radically improve the Help feature.&lt;/p&gt;&lt;/div&gt;</body-html>
      <closed type="boolean">false</closed>
      <created-at type="datetime">2011-05-13T07:35:24+09:00</created-at>
      <creator-id type="integer">2503</creator-id>
      <diffable-attributes type="yaml">--- {}

</diffable-attributes>
      <milestone-id type="integer">90248</milestone-id>
      <number type="integer">252</number>
      <permalink>notations-add-ability-to-use-wysiwyg-in-help</permalink>
      <priority type="integer">1</priority>
      <project-id type="integer">30780</project-id>
      <state>new</state>
      <tag nil="true"></tag>
      <title>Notations &gt; Add ability to use wysiwyg in Help</title>
      <updated-at type="datetime">2011-05-13T07:36:03+09:00</updated-at>
      <user-id type="integer">2503</user-id>
      <version type="integer">1</version>
      <user-name>Anatole</user-name>
      <creator-name>Anatole</creator-name>
      <url>http://theplant.lighthouseapp.com/projects/30780/tickets/252</url>
      <milestone-title>Next Milestone?</milestone-title>
      <priority-name>High</priority-name>
    </version>
  </versions>
</ticket>
