<?xml version="1.0" encoding="UTF-8"?>
<ticket>
  <assigned-user-id type="integer">154128</assigned-user-id>
  <attachments-count type="integer">4</attachments-count>
  <closed type="boolean">false</closed>
  <created-at type="datetime">2011-09-17T16:30:35+09:00</created-at>
  <creator-id type="integer">95021</creator-id>
  <milestone-due-on type="datetime">2011-08-03T00:00:00+09:00</milestone-due-on>
  <milestone-id type="integer">117173</milestone-id>
  <number type="integer">856</number>
  <permalink>ie78cant-show-subscribing-confirm-message</permalink>
  <priority type="integer">3</priority>
  <project-id type="integer">55575</project-id>
  <raw-data type="binary" nil="true" encoding="base64"></raw-data>
  <state>new</state>
  <tag nil="true"></tag>
  <title>IE7/8&gt;can't show subscribing confirm  message </title>
  <updated-at type="datetime">2011-09-20T12:00:27+09:00</updated-at>
  <user-id type="integer">94027</user-id>
  <version type="integer">2</version>
  <user-name>bin</user-name>
  <creator-name>Tingting</creator-name>
  <assigned-user-name>Yuan He</assigned-user-name>
  <url>http://theplant.lighthouseapp.com/projects/55575/tickets/856</url>
  <milestone-title>Current Iteration</milestone-title>
  <priority-name>Low</priority-name>
  <original-body>click the link to confirm subscribing, but the message don't show, alway loading the ajax loader icon.</original-body>
  <latest-body>click the link to confirm subscribing, but the message don't show, alway loading the ajax loader icon.</latest-body>
  <original-body-html>&lt;div&gt;&lt;p&gt;click the link to confirm subscribing, but the message don't
show, alway loading the ajax loader icon.&lt;/p&gt;&lt;/div&gt;</original-body-html>
  <versions type="array">
    <version type="Ticket::Version">
      <assigned-user-id type="integer">94027</assigned-user-id>
      <attachments-count type="integer">0</attachments-count>
      <body>click the link to confirm subscribing, but the message don't show, alway loading the ajax loader icon.</body>
      <body-html>&lt;div&gt;&lt;p&gt;click the link to confirm subscribing, but the message don't
show, alway loading the ajax loader icon.&lt;/p&gt;&lt;/div&gt;</body-html>
      <closed type="boolean">false</closed>
      <created-at type="datetime">2011-09-17T16:30:35+09:00</created-at>
      <creator-id type="integer">95021</creator-id>
      <diffable-attributes type="yaml">--- {}

</diffable-attributes>
      <milestone-id type="integer">117173</milestone-id>
      <number type="integer">856</number>
      <permalink>ie78cant-show-subscribing-confirm-message</permalink>
      <priority type="integer">3</priority>
      <project-id type="integer">55575</project-id>
      <state>new</state>
      <tag nil="true"></tag>
      <title>IE7/8&gt;can't show subscribing confirm  message </title>
      <updated-at type="datetime">2011-09-17T16:30:48+09:00</updated-at>
      <user-id type="integer">95021</user-id>
      <version type="integer">1</version>
      <user-name>Tingting</user-name>
      <creator-name>Tingting</creator-name>
      <assigned-user-name>bin</assigned-user-name>
      <url>http://theplant.lighthouseapp.com/projects/55575/tickets/856</url>
      <milestone-title>Current Iteration</milestone-title>
      <priority-name>Low</priority-name>
    </version>
    <version type="Ticket::Version">
      <assigned-user-id type="integer">154128</assigned-user-id>
      <attachments-count type="integer">4</attachments-count>
      <body></body>
      <body-html></body-html>
      <closed type="boolean">false</closed>
      <created-at type="datetime">2011-09-20T12:00:06+09:00</created-at>
      <creator-id type="integer">95021</creator-id>
      <diffable-attributes type="yaml">--- 
:assigned_user: 94027
</diffable-attributes>
      <milestone-id type="integer">117173</milestone-id>
      <number type="integer">856</number>
      <permalink>ie78cant-show-subscribing-confirm-message</permalink>
      <priority type="integer">3</priority>
      <project-id type="integer">55575</project-id>
      <state>new</state>
      <tag nil="true"></tag>
      <title>IE7/8&gt;can't show subscribing confirm  message </title>
      <updated-at type="datetime">2011-09-20T12:00:27+09:00</updated-at>
      <user-id type="integer">94027</user-id>
      <version type="integer">2</version>
      <user-name>bin</user-name>
      <creator-name>Tingting</creator-name>
      <assigned-user-name>Yuan He</assigned-user-name>
      <url>http://theplant.lighthouseapp.com/projects/55575/tickets/856</url>
      <milestone-title>Current Iteration</milestone-title>
      <priority-name>Low</priority-name>
    </version>
  </versions>
  <attachments type="array">
    <attachment-image type="Attachment">
      <code>b5a88927212a6e7037fa129ecc9124b9f416b2d6</code>
      <content-type>image/png</content-type>
      <created-at type="datetime">2011-09-17T16:30:35+09:00</created-at>
      <filename>2011-09-17_1524.png</filename>
      <height type="integer">678</height>
      <id type="integer">1399222</id>
      <size type="integer">567027</size>
      <uploader-id type="integer">95021</uploader-id>
      <width type="integer">1230</width>
      <url>http://theplant.lighthouseapp.com/attachments/1399222/2011-09-17_1524.png</url>
    </attachment-image>
  </attachments>
</ticket>
